pyforge_cli/__init__.py
pyforge_cli/_version.py
pyforge_cli/main.py
pyforge_cli/backends/__init__.py
pyforge_cli/backends/base.py
pyforge_cli/backends/jar_manager.py
pyforge_cli/backends/pyodbc_backend.py
pyforge_cli/backends/ucanaccess_backend.py
pyforge_cli/backends/ucanaccess_subprocess_backend.py
pyforge_cli/converters/__init__.py
pyforge_cli/converters/base.py
pyforge_cli/converters/csv_converter.py
pyforge_cli/converters/dbf_converter.py
pyforge_cli/converters/enhanced_mdb_converter.py
pyforge_cli/converters/excel_converter.py
pyforge_cli/converters/excel_table_detector.py
pyforge_cli/converters/mdb_converter.py
pyforge_cli/converters/pdf_converter.py
pyforge_cli/converters/pyspark_csv_converter.py
pyforge_cli/converters/string_database_converter.py
pyforge_cli/converters/xml.py
pyforge_cli/converters/xml_flattener.py
pyforge_cli/converters/xml_structure_analyzer.py
pyforge_cli/data/jars/commons-lang3-3.8.1.jar
pyforge_cli/data/jars/commons-logging-1.2.jar
pyforge_cli/data/jars/hsqldb-2.5.0.jar
pyforge_cli/data/jars/jackcess-3.0.1.jar
pyforge_cli/data/jars/ucanaccess-4.0.4.jar
pyforge_cli/data/jars/ucanaccess-5.0.1.jar
pyforge_cli/data/jars/ucanaccess-5.1.2-all.jar
pyforge_cli/data/jars/ucanaccess-5.1.3-uber.jar
pyforge_cli/databricks/__init__.py
pyforge_cli/databricks/environment.py
pyforge_cli/detectors/__init__.py
pyforge_cli/detectors/database_detector.py
pyforge_cli/installers/__init__.py
pyforge_cli/installers/mdf_tools_installer.py
pyforge_cli/installers/sample_datasets_installer.py
pyforge_cli/plugins/__init__.py
pyforge_cli/plugins/loader.py
pyforge_cli/plugins/registry.py
pyforge_cli/readers/__init__.py
pyforge_cli/readers/dbf_reader.py
pyforge_cli/readers/dual_backend_mdb_reader.py
pyforge_cli/readers/mdb_reader.py
pyforge_cli/utils/dependency_checker.py
pyforge_cli-1.0.9.dist-info/licenses/LICENSE
pyforge_cli-1.0.9.dist-info/METADATA
pyforge_cli-1.0.9.dist-info/WHEEL
pyforge_cli-1.0.9.dist-info/entry_points.txt
pyforge_cli-1.0.9.dist-info/top_level.txt
pyforge_cli-1.0.9.dist-info/RECORD
