Metadata-Version: 2.4
Name: pyforge-cli
Version: 1.0.9
Summary: A powerful CLI tool for data format conversion and synthetic data generation
Author-email: Santosh Dandey <dd.santosh@gmail.com>
License: MIT
Project-URL: Homepage, https://github.com/Py-Forge-Cli/PyForge-CLI
Project-URL: Repository, https://github.com/Py-Forge-Cli/PyForge-CLI
Project-URL: Issues, https://github.com/Py-Forge-Cli/PyForge-CLI/issues
Project-URL: Documentation, https://github.com/Py-Forge-Cli/PyForge-CLI/blob/main/docs
Project-URL: Changelog, https://github.com/Py-Forge-Cli/PyForge-CLI/blob/main/CHANGELOG.md
Keywords: cli,data,conversion,pdf,csv,parquet,excel,database,mdb,dbf,synthetic-data
Classifier: Development Status :: 4 - Beta
Classifier: Environment :: Console
Classifier: Intended Audience :: Developers
Classifier: Intended Audience :: System Administrators
Classifier: Intended Audience :: Information Technology
Classifier: License :: OSI Approved :: MIT License
Classifier: Operating System :: OS Independent
Classifier: Operating System :: MacOS
Classifier: Operating System :: Microsoft :: Windows
Classifier: Operating System :: POSIX :: Linux
Classifier: Programming Language :: Python :: 3
Classifier: Programming Language :: Python :: 3.8
Classifier: Programming Language :: Python :: 3.9
Classifier: Programming Language :: Python :: 3.10
Classifier: Programming Language :: Python :: 3.11
Classifier: Programming Language :: Python :: 3.12
Classifier: Programming Language :: Python :: 3 :: Only
Classifier: Topic :: Database :: Database Engines/Servers
Classifier: Topic :: Office/Business
Classifier: Topic :: Software Development :: Libraries :: Python Modules
Classifier: Topic :: System :: Archiving
Classifier: Topic :: Text Processing :: Markup
Classifier: Topic :: Utilities
Requires-Python: >=3.8
License-File: LICENSE
Requires-Dist: pandas==1.5.3
Requires-Dist: pyarrow==8.0.0
Requires-Dist: numpy==1.23.5
Requires-Dist: pytz==2022.7
Requires-Dist: python-dateutil==2.8.2
Requires-Dist: six==1.16.0
Requires-Dist: click==8.1.3
Requires-Dist: rich==12.6.0
Requires-Dist: jaydebeapi>=1.2.3
Requires-Dist: jpype1>=1.3.0
Requires-Dist: openpyxl>=3.0.0
Requires-Dist: dbfread>=2.0.0
Requires-Dist: PyMuPDF>=1.20.0
Requires-Dist: chardet>=3.0.0
Requires-Dist: requests>=2.25.0
Provides-Extra: ucanaccess
Requires-Dist: jaydebeapi>=1.2.3; extra == "ucanaccess"
Requires-Dist: jpype1>=1.3.0; extra == "ucanaccess"
Provides-Extra: excel
Requires-Dist: openpyxl>=3.0.0; extra == "excel"
Provides-Extra: dbf
Requires-Dist: dbfread>=2.0.7; extra == "dbf"
Provides-Extra: pdf
Requires-Dist: PyMuPDF>=1.20.0; extra == "pdf"
Provides-Extra: ui
Requires-Dist: rich>=12.0.0; extra == "ui"
Requires-Dist: tqdm>=4.60.0; extra == "ui"
Provides-Extra: utils
Requires-Dist: pathlib-mate>=1.0.0; extra == "utils"
Provides-Extra: all
Requires-Dist: jaydebeapi>=1.2.3; extra == "all"
Requires-Dist: jpype1>=1.3.0; extra == "all"
Requires-Dist: openpyxl>=3.0.0; extra == "all"
Requires-Dist: dbfread>=2.0.7; extra == "all"
Requires-Dist: PyMuPDF>=1.20.0; extra == "all"
Requires-Dist: rich>=12.0.0; extra == "all"
Requires-Dist: tqdm>=4.60.0; extra == "all"
Requires-Dist: pathlib-mate>=1.0.0; extra == "all"
Requires-Dist: pandas-access>=0.0.1; extra == "all"
Requires-Dist: docker>=5.0.0; extra == "all"
Requires-Dist: pyodbc>=4.0.0; sys_platform == "win32" and extra == "all"
Provides-Extra: dev
Requires-Dist: pytest>=7.0.0; extra == "dev"
Requires-Dist: pytest-cov>=4.0.0; extra == "dev"
Requires-Dist: pytest-mock>=3.10.0; extra == "dev"
Requires-Dist: black>=23.0.0; extra == "dev"
Requires-Dist: ruff>=0.1.0; extra == "dev"
Requires-Dist: isort>=5.12.0; extra == "dev"
Requires-Dist: mypy>=1.0.0; extra == "dev"
Requires-Dist: types-requests; extra == "dev"
Requires-Dist: bandit[toml]>=1.7.5; extra == "dev"
Requires-Dist: safety>=2.3.0; extra == "dev"
Requires-Dist: pre-commit>=3.0.0; extra == "dev"
Requires-Dist: build>=0.10.0; extra == "dev"
Requires-Dist: twine>=4.0.0; extra == "dev"
Provides-Extra: test
Requires-Dist: pytest>=7.0.0; extra == "test"
Requires-Dist: pytest-cov>=4.0.0; extra == "test"
Requires-Dist: pytest-mock>=3.10.0; extra == "test"
Provides-Extra: docs
Requires-Dist: mkdocs>=1.4.0; extra == "docs"
Requires-Dist: mkdocs-material>=9.0.0; extra == "docs"
Requires-Dist: mkdocs-mermaid2-plugin>=0.6.0; extra == "docs"
Dynamic: license-file
